<databaseChangeLog
    xmlns="http://www.liquibase.org/xml/ns/dbchangelog"
    xmlns:xsi="http://www.w3.org/2001/XMLSchema-instance"
    xmlns:ext="http://www.liquibase.org/xml/ns/dbchangelog-ext"
    xsi:schemaLocation="http://www.liquibase.org/xml/ns/dbchangelog http://www.liquibase.org/xml/ns/dbchangelog/dbchangelog-3.0.xsd
    http://www.liquibase.org/xml/ns/dbchangelog-ext http://www.liquibase.org/xml/ns/dbchangelog/dbchangelog-ext.xsd">
    <!-- 
    	ChangeSet ID pattern :
    		<A.A.A>-<BB>.<C>-<XXXX>
    		A.A.A : Version in which appli the changeset
    		BB : ChangeSet incremented number of this version : MUST match the sql file prefixes
    		C : Step of changeSet (you may sometime need to separate some change)
    		XXXX: short label of the changeset
    	N.B : the 0.0.1-00.0 to 0.0.1-00.3 changeset doesn't apply these rules properly  
     -->
    <changeSet id="0.0.1-00.0-createTables" author="adi3000">
    	<validCheckSum>7:13bd1974f63086c52eaed109e5e0c6ab</validCheckSum>
    	<sqlFile
    			relativeToChangelogFile="true" 
    			path="0.0.1/modeling/00-create_main_tables.sql"/>
    			
    	<rollback>
    		<sqlFile
    				relativeToChangelogFile="true" 
    				path="0.0.1/modeling/00-create_main_tables.rollback.sql"/>
    	</rollback>
    </changeSet>
    <changeSet id="0.0.1-00.1-referentiel" author="adi3000" context="production">
   	 	<sqlFile
    			relativeToChangelogFile="true" 
    			path="0.0.1/referentiel/00-create_parameters.sql"/>
   	 	<sqlFile
    			relativeToChangelogFile="true" 
    			path="0.0.1/referentiel/00-create_referentiel.sql"/>
   	 	<sqlFile
    			relativeToChangelogFile="true" 
    			path="0.0.1/referentiel/00-create_places.sql"/>
    </changeSet>
    <changeSet id="0.0.1-00.1-test-referentiel" author="adi3000" context="test">
   	 	<sqlFile
    			relativeToChangelogFile="true" 
    			path="0.0.1/referentiel/00-create_parameters.sql"/>
   	 	<sqlFile
    			relativeToChangelogFile="true" 
    			path="0.0.1/referentiel/00-create_referentiel.sql"/>
    </changeSet>
    <changeSet id="0.0.1-00.2-parameter" author="adi3000">
   	 	<sqlFile
    			relativeToChangelogFile="true" 
    			path="0.0.1/referentiel/01-create_parameters.sql"/>
    </changeSet>
    <changeSet id="0.0.1-00.3-parameter" author="adi3000">
        <validCheckSum>7:236eb9d992d6c2e006cc304900ab613d</validCheckSum>
   	 	<sqlFile
    			relativeToChangelogFile="true" 
    			path="0.0.1/modeling/03-create_navigation_table.sql"/>
   	 	<sqlFile
    			relativeToChangelogFile="true" 
    			path="0.0.1/referentiel/03-init_navigation_map.sql"/>
    </changeSet>
    <changeSet id="0.0.1-00.4-items_keywords" author="adi3000" context="test">
   	 	<sqlFile
    			relativeToChangelogFile="true" 
    			path="0.0.1/modeling/04-create_items_keywords_tables.sql"/>
    </changeSet>
    <changeSet id="0.0.1-05.0-items_keywords" author="adi3000">
   	 	<sqlFile
    			relativeToChangelogFile="true" 
    			path="0.0.1/referentiel/05-create_parameters.sql"/>
    </changeSet>
    <changeSet id="0.0.1-06.0-items_keywords" author="adi3000">
   	 	<sqlFile
    			relativeToChangelogFile="true" 
    			path="0.0.1/modeling/06-smf_authentication.sql"/>
    </changeSet>
    <changeSet id="0.0.1-06.9-forum_schema" author="adi3000">
   	 	<sqlFile
    			relativeToChangelogFile="true"
    			path="0.0.1/modeling/07-0-add_forum_shema.sql"/>
    </changeSet>
    <changeSet id="0.0.1-07.0-admin_console" author="adi3000">
   	 	<sqlFile
    			relativeToChangelogFile="true" 
    			path="0.0.1/modeling/07-admin_console.sql"/>
   	 	<sqlFile
    			relativeToChangelogFile="true" 
    			path="0.0.1/referentiel/07-create-roles.sql"/>
    </changeSet>
    <changeSet id="0.0.1-08.0-rename_location_to_place" author="adi3000">
   	 	<sqlFile
    			relativeToChangelogFile="true" 
    			path="0.0.1/modeling/08-rename_location_to_places.sql"/>
    </changeSet>
    <changeSet id="0.0.1-09.0-security_upgrade" author="adi3000">
   	 	<sqlFile
    			relativeToChangelogFile="true" 
    			path="0.0.1/modeling/09-security_upgrade.sql"/>
    </changeSet>
    <changeSet id="0.0.1-10.0-adding_parameters" author="adi3000">
   	 	<sqlFile
    			relativeToChangelogFile="true" 
    			path="0.0.1/referentiel/10-supply_more_parameters.sql"/>
    </changeSet>
</databaseChangeLog>